{"name":"build-javascript","namedChunkGroups":{"polyfill":{"name":"polyfill","assets":[{"name":"webpack-runtime-b40af272ea91637c8c13.js","size":5121},{"name":"polyfill-4718f0fec20e0d09d7f5.js","size":85862}],"filteredAssets":0,"assetsSize":90983,"filteredAuxiliaryAssets":2,"auxiliaryAssetsSize":225762},"app":{"name":"app","assets":[{"name":"webpack-runtime-b40af272ea91637c8c13.js","size":5121},{"name":"framework-c4c052d1b2b22de01269.js","size":149109},{"name":"app-a5f5470ddf41e63560da.js","size":115057}],"filteredAssets":0,"assetsSize":269287,"filteredAuxiliaryAssets":3,"auxiliaryAssetsSize":927869},"component---src-pages-404-tsx":{"name":"component---src-pages-404-tsx","assets":[{"name":"1a48c3c1-3a94bcd769c287f33b43.js","size":1167},{"name":"commons-e756ce98dfaf4ed71029.js","size":27984},{"name":"component---src-pages-404-tsx-afd21f2521ec69d3ce6f.js","size":329}],"filteredAssets":0,"assetsSize":29480,"filteredAuxiliaryAssets":3,"auxiliaryAssetsSize":570187},"component---src-pages-about-tsx":{"name":"component---src-pages-about-tsx","assets":[{"name":"1a48c3c1-3a94bcd769c287f33b43.js","size":1167},{"name":"1bfc9850-de235500ad4e3f6d6339.js","size":2393},{"name":"commons-e756ce98dfaf4ed71029.js","size":27984},{"name":"component---src-pages-about-tsx-f142742213d0049a1c83.js","size":2318}],"filteredAssets":0,"assetsSize":33862,"filteredAuxiliaryAssets":4,"auxiliaryAssetsSize":2098132},"component---src-pages-blog-tsx":{"name":"component---src-pages-blog-tsx","assets":[{"name":"1a48c3c1-3a94bcd769c287f33b43.js","size":1167},{"name":"commons-e756ce98dfaf4ed71029.js","size":27984},{"name":"component---src-pages-blog-tsx-e1beac2b2fcd7e5d92e1.js","size":3317}],"filteredAssets":0,"assetsSize":32468,"filteredAuxiliaryAssets":3,"auxiliaryAssetsSize":578567},"component---src-pages-category-tsx":{"name":"component---src-pages-category-tsx","assets":[{"name":"1a48c3c1-3a94bcd769c287f33b43.js","size":1167},{"name":"commons-e756ce98dfaf4ed71029.js","size":27984},{"name":"component---src-pages-category-tsx-21984ab9667151583f04.js","size":1518}],"filteredAssets":0,"assetsSize":30669,"filteredAuxiliaryAssets":3,"auxiliaryAssetsSize":573515},"component---src-pages-index-tsx":{"name":"component---src-pages-index-tsx","assets":[{"name":"1a48c3c1-3a94bcd769c287f33b43.js","size":1167},{"name":"1bfc9850-de235500ad4e3f6d6339.js","size":2393},{"name":"commons-e756ce98dfaf4ed71029.js","size":27984},{"name":"component---src-pages-index-tsx-c1265cdfe63c9909917f.js","size":2208}],"filteredAssets":0,"assetsSize":33752,"filteredAuxiliaryAssets":4,"auxiliaryAssetsSize":2097816},"component---src-templates-category-template-tsx":{"name":"component---src-templates-category-template-tsx","assets":[{"name":"1a48c3c1-3a94bcd769c287f33b43.js","size":1167},{"name":"commons-e756ce98dfaf4ed71029.js","size":27984},{"name":"component---src-templates-category-template-tsx-b7d998e8bd74e36e61ee.js","size":3357}],"filteredAssets":0,"assetsSize":32508,"filteredAuxiliaryAssets":3,"auxiliaryAssetsSize":578868},"component---src-templates-post-template-tsx":{"name":"component---src-templates-post-template-tsx","assets":[{"name":"1a48c3c1-3a94bcd769c287f33b43.js","size":1167},{"name":"commons-e756ce98dfaf4ed71029.js","size":27984},{"name":"component---src-templates-post-template-tsx-89ed1f621cba5ee9e436.js","size":13066}],"filteredAssets":0,"assetsSize":42217,"filteredAuxiliaryAssets":3,"auxiliaryAssetsSize":645879}},"assetsByChunkName":{"polyfill":["webpack-runtime-b40af272ea91637c8c13.js","polyfill-4718f0fec20e0d09d7f5.js"],"app":["webpack-runtime-b40af272ea91637c8c13.js","framework-c4c052d1b2b22de01269.js","app-a5f5470ddf41e63560da.js"],"component---src-pages-404-tsx":["1a48c3c1-3a94bcd769c287f33b43.js","commons-e756ce98dfaf4ed71029.js","component---src-pages-404-tsx-afd21f2521ec69d3ce6f.js"],"component---src-pages-about-tsx":["1a48c3c1-3a94bcd769c287f33b43.js","1bfc9850-de235500ad4e3f6d6339.js","commons-e756ce98dfaf4ed71029.js","component---src-pages-about-tsx-f142742213d0049a1c83.js"],"component---src-pages-blog-tsx":["1a48c3c1-3a94bcd769c287f33b43.js","commons-e756ce98dfaf4ed71029.js","component---src-pages-blog-tsx-e1beac2b2fcd7e5d92e1.js"],"component---src-pages-category-tsx":["1a48c3c1-3a94bcd769c287f33b43.js","commons-e756ce98dfaf4ed71029.js","component---src-pages-category-tsx-21984ab9667151583f04.js"],"component---src-pages-index-tsx":["1a48c3c1-3a94bcd769c287f33b43.js","1bfc9850-de235500ad4e3f6d6339.js","commons-e756ce98dfaf4ed71029.js","component---src-pages-index-tsx-c1265cdfe63c9909917f.js"],"component---src-templates-category-template-tsx":["1a48c3c1-3a94bcd769c287f33b43.js","commons-e756ce98dfaf4ed71029.js","component---src-templates-category-template-tsx-b7d998e8bd74e36e61ee.js"],"component---src-templates-post-template-tsx":["1a48c3c1-3a94bcd769c287f33b43.js","commons-e756ce98dfaf4ed71029.js","component---src-templates-post-template-tsx-89ed1f621cba5ee9e436.js"]},"childAssetsByChunkName":{}}